{
  "manifestVersion": "3.2",
  "admin": {
    "address": "0x54Bb697A1DcBe96b9b6Fd314b54831Fc7Cb89018",
    "txHash": "0xeffc921fc3fae7a54257564121a2db5ca2c17e707796f0387e0e28f0e2d2b91e"
  },
  "proxies": [
    {
      "address": "0xc336cfCe2942CC7ae8c687a661020a390BB25a22",
      "txHash": "0x1b5f04f51ae4b54e382696da62d5c37ffa7e2361f2aaaf17e14feb5b8708c0e3",
      "kind": "transparent"
    }
  ],
  "impls": {
    "2b0317e094c2d38d58a6073fc8abb972e2698c8dcc5f7c1df93c8ac985b0c992": {
      "address": "0x1e4674Ee68A13448B1fE233cCe6f062d44EBF017",
      "txHash": "0x6409dd06b9099e5d5a5aa5a7abb3e67318008272fcd7ca0134cfd5e7dafd6df5",
      "layout": {
        "solcVersion": "0.8.15",
        "storage": [
          {
            "label": "_familyIdExists",
            "offset": 0,
            "slot": "0",
            "type": "t_mapping(t_bytes32,t_bool)",
            "contract": "Host",
            "src": "src/Host.sol:14"
          },
          {
            "label": "_familyByOwner",
            "offset": 0,
            "slot": "1",
            "type": "t_mapping(t_address,t_struct(Family)72_storage)",
            "contract": "Host",
            "src": "src/Host.sol:15"
          },
          {
            "label": "_familyIdByOwner",
            "offset": 0,
            "slot": "2",
            "type": "t_mapping(t_address,t_bytes32)",
            "contract": "Host",
            "src": "src/Host.sol:16"
          },
          {
            "label": "_userTypeByAddress",
            "offset": 0,
            "slot": "3",
            "type": "t_mapping(t_address,t_uint24)",
            "contract": "Host",
            "src": "src/Host.sol:17"
          },
          {
            "label": "_childByFamilyId",
            "offset": 0,
            "slot": "4",
            "type": "t_mapping(t_bytes32,t_mapping(t_address,t_struct(Child)58_storage))",
            "contract": "Host",
            "src": "src/Host.sol:18"
          }
        ],
        "types": {
          "t_address": {
            "label": "address",
            "numberOfBytes": "20"
          },
          "t_address_payable": {
            "label": "address payable",
            "numberOfBytes": "20"
          },
          "t_array(t_address)dyn_storage": {
            "label": "address[]",
            "numberOfBytes": "32"
          },
          "t_bool": {
            "label": "bool",
            "numberOfBytes": "1"
          },
          "t_bytes32": {
            "label": "bytes32",
            "numberOfBytes": "32"
          },
          "t_mapping(t_address,t_bytes32)": {
            "label": "mapping(address => bytes32)",
            "numberOfBytes": "32"
          },
          "t_mapping(t_address,t_struct(Child)58_storage)": {
            "label": "mapping(address => struct Host.Child)",
            "numberOfBytes": "32"
          },
          "t_mapping(t_address,t_struct(Family)72_storage)": {
            "label": "mapping(address => struct Host.Family)",
            "numberOfBytes": "32"
          },
          "t_mapping(t_address,t_uint24)": {
            "label": "mapping(address => uint24)",
            "numberOfBytes": "32"
          },
          "t_mapping(t_bytes32,t_bool)": {
            "label": "mapping(bytes32 => bool)",
            "numberOfBytes": "32"
          },
          "t_mapping(t_bytes32,t_mapping(t_address,t_struct(Child)58_storage))": {
            "label": "mapping(bytes32 => mapping(address => struct Host.Child))",
            "numberOfBytes": "32"
          },
          "t_string_storage": {
            "label": "string",
            "numberOfBytes": "32"
          },
          "t_struct(Child)58_storage": {
            "label": "struct Host.Child",
            "members": [
              {
                "label": "username",
                "type": "t_string_storage",
                "offset": 0,
                "slot": "0"
              },
              {
                "label": "avatarURI",
                "type": "t_string_storage",
                "offset": 0,
                "slot": "1"
              },
              {
                "label": "familyId",
                "type": "t_bytes32",
                "offset": 0,
                "slot": "2"
              },
              {
                "label": "memberSince",
                "type": "t_uint256",
                "offset": 0,
                "slot": "3"
              },
              {
                "label": "wallet",
                "type": "t_address",
                "offset": 0,
                "slot": "4"
              },
              {
                "label": "sandboxMode",
                "type": "t_bool",
                "offset": 20,
                "slot": "4"
              }
            ],
            "numberOfBytes": "160"
          },
          "t_struct(Family)72_storage": {
            "label": "struct Host.Family",
            "members": [
              {
                "label": "familyId",
                "type": "t_bytes32",
                "offset": 0,
                "slot": "0"
              },
              {
                "label": "memberSince",
                "type": "t_uint256",
                "offset": 0,
                "slot": "1"
              },
              {
                "label": "avatarURI",
                "type": "t_string_storage",
                "offset": 0,
                "slot": "2"
              },
              {
                "label": "username",
                "type": "t_string_storage",
                "offset": 0,
                "slot": "3"
              },
              {
                "label": "owner",
                "type": "t_address_payable",
                "offset": 0,
                "slot": "4"
              },
              {
                "label": "children",
                "type": "t_array(t_address)dyn_storage",
                "offset": 0,
                "slot": "5"
              }
            ],
            "numberOfBytes": "192"
          },
          "t_uint24": {
            "label": "uint24",
            "numberOfBytes": "3"
          },
          "t_uint256": {
            "label": "uint256",
            "numberOfBytes": "32"
          }
        }
      }
    }
  }
}
